SimpleAgents/__init__.py
SimpleAgents/agent.py
SimpleAgents/long_memory.py
SimpleAgents/memory_manager.py
SimpleAgents/short_memory.py
openai_simple_agents-0.0.45.dist-info/licenses/LICENSE
openai_simple_agents-0.0.45.dist-info/METADATA
openai_simple_agents-0.0.45.dist-info/WHEEL
openai_simple_agents-0.0.45.dist-info/top_level.txt
openai_simple_agents-0.0.45.dist-info/RECORD
