Metadata-Version: 2.4
Name: openai-simple-agents
Version: 0.0.45
Summary: Асинхронная архитектура памяти для OpenAI-агентов на базе ChromaDB и SQLite
Author-email: Платановский Дмитрий Алексеевич <platanovskiydmitriy@gmail.com>
License: MIT
Project-URL: Homepage, https://github.com/your-username/simple-agents
Project-URL: Repository, https://github.com/your-username/simple-agents
Classifier: Programming Language :: Python :: 3.11
Classifier: License :: OSI Approved :: MIT License
Classifier: Operating System :: OS Independent
Classifier: Intended Audience :: Developers
Classifier: Topic :: Scientific/Engineering :: Artificial Intelligence
Requires-Python: >=3.11
License-File: LICENSE
Requires-Dist: openai>=1.14.2
Requires-Dist: chromadb>=0.4.22
Requires-Dist: tiktoken>=0.6.0
Requires-Dist: aiosqlite
Provides-Extra: dev
Requires-Dist: pytest>=7.4.0; extra == "dev"
Requires-Dist: pytest-asyncio>=0.21.0; extra == "dev"
Requires-Dist: sentence-transformers>=2.2.2; extra == "dev"
Requires-Dist: mypy>=1.7.0; extra == "dev"
Requires-Dist: black>=24.3.0; extra == "dev"
Requires-Dist: isort>=5.12.0; extra == "dev"
Dynamic: license-file
